yeahyeah/__init__.py
yeahyeah/cli.py
yeahyeah/config.py
yeahyeah/context.py
yeahyeah/core.py
yeahyeah/decorators.py
yeahyeah/exceptions.py
yeahyeah/objects.py
yeahyeah/persistence.py
yeahyeah/plugin_testing.py
yeahyeah_plugins/__init__.py
yeahyeah_plugins/clockify_plugin/__init__.py
yeahyeah_plugins/clockify_plugin/cli.py
yeahyeah_plugins/clockify_plugin/context.py
yeahyeah_plugins/clockify_plugin/core.py
yeahyeah_plugins/clockify_plugin/decorators.py
yeahyeah_plugins/clockify_plugin/parameters.py
yeahyeah_plugins/clockify_plugin/time.py
yeahyeah_plugins/path_item_plugin/__init__.py
yeahyeah_plugins/path_item_plugin/core.py
yeahyeah_plugins/url_pattern_plugin/__init__.py
yeahyeah_plugins/url_pattern_plugin/core.py
yeahyeah-0.4.5.dist-info/AUTHORS.rst
yeahyeah-0.4.5.dist-info/LICENSE
yeahyeah-0.4.5.dist-info/METADATA
yeahyeah-0.4.5.dist-info/WHEEL
yeahyeah-0.4.5.dist-info/entry_points.txt
yeahyeah-0.4.5.dist-info/top_level.txt
yeahyeah-0.4.5.dist-info/RECORD
