Metadata-Version: 2.1
Name: yeahyeah
Version: 0.4.5
Summary: Command line launch manager. Do things quick yeah yeah I know just do it come on move
Home-page: https://github.com/sjoerdk/yeahyeah
Author: Sjoerd Kerkstra
Author-email: w.s.kerkstra@protonmail.com
License: MIT license
Keywords: yeahyeah
Platform: UNKNOWN
Classifier: Development Status :: 2 - Pre-Alpha
Classifier: Intended Audience :: Developers
Classifier: License :: OSI Approved :: MIT License
Classifier: Natural Language :: English
Classifier: Programming Language :: Python :: 3.7
Requires-Dist: Click >=6.0
Requires-Dist: pyyaml
Requires-Dist: clockifyclient
Requires-Dist: python-dateutil
